{
  "article_id": "15553713751065",
  "title": "Malayan Insurance Pet Insure (Dogs Only)",
  "url": "https://help.gcash.com/hc/en-us/articles/15553713751065-Malayan-Insurance-Pet-Insure-Dogs-Only",
  "content": "#### ADVISORY:\n\nBank Transfer to Maya will be right back! Our partner is working to restore the service as soon as possible.\n\n## Articles in this section\n\n- [Malayan Insurance Pet Insure (Dogs Only)](https://help.gcash.com/hc/en-us/articles/15553713751065-Malayan-Insurance-Pet-Insure-Dogs-Only)\n- [Standard Insurance Pet Health](https://help.gcash.com/hc/en-us/articles/15552480131225-Standard-Insurance-Pet-Health)\n\n## Promoted articles\n\n- [What are the steps to get a Fully Verified GCash account?](https://help.gcash.com/hc/en-us/articles/360017722393-What-are-the-steps-to-get-a-Fully-Verified-GCash-account)\n- [Accepted IDs for GCash Verification](https://help.gcash.com/hc/en-us/articles/900000948786-Accepted-IDs-for-GCash-Verification)\n- [How do I send money to another GCash account?](https://help.gcash.com/hc/en-us/articles/360017566614-How-do-I-send-money-to-another-GCash-account)\n\nMalayan Insurance Pet Insure is an insurance designed for furbabies and pawrents. Pet Insure offers a 3-in-1 package benefit such as Medical Reimbursement, Pet Owner’s Liability, and 24/7 pet owner’s personal accident cover.\n\nJump to:\n\n- [Coverage](https://help.gcash.com/hc/en-us/articles/15553713751065-Malayan-Insurance-Pet-Insure-Dogs-Only#h_01H3BW8R449NC6YWTNXKVFVGGV)\n- [Eligibility](https://help.gcash.com/hc/en-us/articles/15553713751065-Malayan-Insurance-Pet-Insure-Dogs-Only#h_01H3BW8WK1MQEKPMTBMCTKX2W2)\n- [Purchase Malayan Insurance Pet Insure](https://help.gcash.com/hc/en-us/articles/15553713751065-Malayan-Insurance-Pet-Insure-Dogs-Only#h_01H3BW9616ZFXQ456YWN1B2CS0)\n- [Claims](https://help.gcash.com/hc/en-us/articles/15553713751065-Malayan-Insurance-Pet-Insure-Dogs-Only#h_01H3EK7KA5D9QDEMT80M6DDPP5)\n- [Cancellation](https://help.gcash.com/hc/en-us/articles/15553713751065-Malayan-Insurance-Pet-Insure-Dogs-Only#h_01H3EK8JMMQVW1WGQGYWVE2NZ3)\n- [Contact Malayan Insurance](https://help.gcash.com/hc/en-us/articles/15553713751065-Malayan-Insurance-Pet-Insure-Dogs-Only#h_01H3BW9F2GK57DTCAPM0ET016K)\n\n## Coverage\n\n**Note**: The owner’s liability covers both bodily injury and property damage caused by the insured dog's actions to a third party. This includes liability if the dog bites a non-insured third party.\n\n| **Products Features and Benefits** | **Limits (in PHP)** |\n| --- | --- |\n| **SECTION 1 – MEDICAL REIMBURSEMENT** |\n| Per Occurrence Limit | 30,000.00 |\n| Annual Aggregate Limit | 100,000.00 |\n| Burial Assistance (due to Euthanasia only) | 10,000.00 |\n| Cruciate Ligament Injuries per Leg (Part of MR limit) | 15,000.00 |\n| **SECTION 2 – OWNERS LIABILITY (THIRD PARTY)** |\n| Per Occurrence Limit | 50,000.00 |\n| Annual Aggregate Limit | 250,000.00 |\n| **SECTION 3 – PERSONAL ACCIDENT COVER\\*** |\n| Accidental Death | 50,000.00 |\n| Total Permanent Disability | 50,000.00 |\n| Disablement or Dismemberment | 50,000.00 |\n\n\\*Limit forms part of and not in addition to the Medical Reimbursement limit\n\n\\*\\*Subject to a maximum accumulated limit of PHP 100,000.00 per Insured pet owner with multiple policies.\n\n\\*\\*\\*Subject to schedule of indemnity relative to extent of injury\n\n| **Deductibles** |\n| --- |\n| Section 1 - <br>Medical Reimbursement | PHP 5,000.00 each and every loss<br>Euthanasia Burial Assistance Benefit – NIL |\n| Section 2 –<br>Owner’s Liability | Third Party Bodily Injury – NIL<br>Third Party Property Damage – 5% of loss amount, minimum of<br>PHP 5,000.00, each and every loss |\n| Section 3 – <br>Personal Accident Cover | NIL |\n\n**Note:** Any veterinarian or clinic is acceptable as long as they are properly licensed by the regulatory bodies.\n\nThe policy does not specify which illnesses are covered. Exclusions include:\n\n1. Conditions related to teeth: Dental issues, such as tooth decay or gum disease, are not covered under our Pet insurance policy\n2. Illnesses for which a vaccine is available: Any illness for which a vaccine is readily available, such as rabies or canine parvovirus, falls under the exclusion list\n3. Illnesses related to anal glands: Conditions affecting the anal glands, including anal gland impaction or infection, are not covered by our policy\n4. Illnesses related to behavior: Illnesses or conditions stemming from behavioral issues, such as anxiety-related disorders or compulsive behaviors, are excluded from our coverage\n5. Inherited or Congenital Disease: Diseases or conditions that are inherited or present at birth, such as hip dysplasia or certain heart conditions, fall under this exclusion\n6. Parasite-related diseases: Illnesses caused by parasites, such as fleas, ticks, or heartworm, are not covered by our Pet insurance policy\n7. Specifically excluded diseases: Some specific diseases or conditions may be explicitly excluded from our coverage. Please refer to your policy documentation for a comprehensive list of such exclusions\n\n## Eligibility\n\nYou can avail of this product if you are:\n\n- 18-65 years old\n- A Filipino or legal resident of the Philippines\n- A [Fully Verified](https://help.gcash.com/hc/en-us/articles/360017722393-How-do-I-get-Fully-Verified-#h_01FPYEDSZ597DXA7JF5NWD6PBC) GCash user\n- An owner of a dog between the age of 6 months and 8 years\n\n## Purchase Malayan Insurance Pet Insure\n\n**Note:** You cannot buy this policy for anyone else. **The insured must be the one to purchase and provide pertinent details and declarations with respect to the pet to be insured. Upgrading of the policy is not allowed.**\n\nThere is no limit to the number of policies each GCash user or pet owner may purchase under their name provided each policy covers a different pet, satisfying that only one (1) policy shall be in force per pet per policy period. Provided further that the maximum allowable accumulated limit for Personal Accident Cover shall be PHP 100,000.00 only, regardless of the number of insured pets or policies in force.\n\n![How_do_I_apply_for_Pet_Insurance.jpg](https://help.gcash.com/hc/article_attachments/15598909252505)\n\n**Note:** Your coverage begins at 12:01 AM Philippine Standard Time the day following the date of activation.\n\n## Claims\n\nTo file a claim for Malayan Insurance Pet Insure, please send a claim request through the [Malayan Claims Form](http://www.malayan.com/claims-and-support/claims-form). Below are the required general documents when filing your claim:\n\n### **General Requirements**\n\n|     |     |\n| --- | --- |\n| Certificate of Cover and Copy of Policy, or Policy Number | Government-issued I.D./Company or School I.D. showing complete home address and signature of Insured, with photo |\n| Pedigree Certificate and/or RFID or microchip scanned serial number, only if submitted during policy issuance | Pet Photo |\n| Written Incident Report |\n\nIn addition to the general requirements, the following documents must be submitted:\n\n### **Section 1 – Medical Reimbursement For Sickness/Illness Claims:**\n\n|     |     |\n| --- | --- |\n| Pet Baby Book/Veterinarian’s Records | Certification of the attending Veterinarian on the illness or nature of treatment and health condition of the pet |\n| Prescription of the Veterinarian for Medical Treatment | Original Receipts of Medical Treatment and Medication of the pet |\n\n**For Accident-Related Claims**\n\n|     |     |\n| --- | --- |\n| Pet Baby Book/Veterinarian’s Records | Certification of the attending Veterinarian on the illness or nature of treatment health condition of the pet |\n| Prescription of the Veterinarian for Medical Treatment | Original Receipts of Medical Treatment on the pet |\n| Police Report or Affidavit of how the accident happened |\n\n**For Burial Assistance Benefits Claims (For Euthanasia only)**\n\n|     |     |\n| --- | --- |\n| Pet Baby Book/Veterinarian’s Records, | Certification of the attending Veterinarian on the illness or nature of treatment  and health condition of the pet |\n| Veterinarian’s Certification and reason for euthanizing the pet. |\n\n### **Section 2 – Owner’s Liability**\n\n**For Third Party Property Damage Claims**\n\n|     |     |\n| --- | --- |\n| Written demand of the third party | Itemized list of damaged property/ies |\n| Photographs of damages items/property | Estimate of repair/replacement of damaged item/invoice/quotation |\n| Quit claim of the third party |\n\n**For Third Party Bodily Injury Claims**\n\n|     |     |\n| --- | --- |\n| Written demand of the third party | Death Certificate (Original/PSA Copy) of third party (in case of death) |\n| Medical Certificate/Clinical/Emergency room report of third party’s bodily injury/ies | Original official receipt/s of medical expenses incurred by third party |\n| Statement of account from the hospital (if confined) | Employment certificate with monthly compensation (if any) |\n| Valid ID of third party | Quit claim of third party |\n\n### **Section 3 – Personal Accident**\n\n**For Accidental Dismemberment and/or Disablement Claims**\n\n|     |     |\n| --- | --- |\n| Certified true copy of Certificate of Confinement or Medical Certificate | Statement of account / hospital billing and records of confinement (original copy) |\n| Operating room report (if an operation was done) | Certification from the attending physician if total disability |\n| Picture of claimant with the affected part |\n\n**For Accidental Death Claims**\n\n|     |     |\n| --- | --- |\n| Valid ID of Insured pet owner and his/her beneficiary | PSA Death Certificate (original and authenticated) |\n| Affidavit of how the accident happened or duly notarized police report | A certified true copy of Post mortem exam if claimant died in the hospital |\n| PSA Marriage Certificate (original and authenticated) – if the beneficiary is the spouse | PSA Birth Certificate of the claimant (original and authenticated) – if the beneficiary is parent/child |\n| PSA Birth Certificate of the claimant and beneficiary (original and authenticated) – if the beneficiary is brother/sister | Filled out Client Information Sheet of the beneficiary |\n\nThe claim proceeds are paid through Fund Transfer. The following are the required documents:\n\n- Certification bearing bank account details (preferably RCBC account; other bank accounts will still be subject for management's approval) duly signed by the Insured. (Template will be provided)\n- Valid ID of the signatory on the release documents\n- Any document that will prove or show Insured's bank details\n- Signed Release Document (Template will be provided)\n\n**Note**: The amount that can be claimed is subject to the submitted official receipts for reimbursement and the limit of coverage. Items excluded from the policy will not be reimbursed.\n\nPet Insure has a waiting period of seven (7) days for one month, fourteen (14) days for three months, and thirty (30) days for six months, nine months, and one year cover from the effectivity of the policy in respect of Section 1 - Medical Reimbursement.\n\nDuring such time, if the pet is diagnosed or suffers from any injuries, sickness, or illness, any expense necessarily incurred to relieve the pet of such condition shall not be recoverable or reimbursable from the policy.\n\n## Cancellation\n\nThe insured may opt to cancel the policy and may be entitled to a premium refund subject to the short-period rate scale. Please contact Malayan Insurance to cancel your policy.\n\n## Contact Malayan Insurance\n\nTo contact Malayan Insurance, please check out their available channels below:\n\n- **Hotline**: +632-8628-8628 or +632-8242-8888 local 8628\n- **Email**: [csc@malayan.com](mailto:csc@malayan.com)\n- **Website**: [https://www.malayan.com/contact-us](https://www.malayan.com/contact-us)\n\n[Previous](https://help.gcash.com/hc/en-us/articles/15553713751065-Malayan-Insurance-Pet-Insure-Dogs-Only#)\n\n[Next](https://help.gcash.com/hc/en-us/articles/15552480131225-Standard-Insurance-Pet-Health)\n\nStandard Insurance Pet Health\n\n- [Malayan Insurance Pet Insure (Dogs Only)](https://help.gcash.com/hc/en-us/articles/15553713751065-Malayan-Insurance-Pet-Insure-Dogs-Only)\n- [Standard Insurance Pet Health](https://help.gcash.com/hc/en-us/articles/15552480131225-Standard-Insurance-Pet-Health)\n\n15553713751065\n\nBack to Top",
  "categories": [
    "Malayan Insurance Pet Insure (Dogs Only)",
    "Standard Insurance Pet Health"
  ],
  "related_articles": [
    {
      "title": "Malayan Insurance Pet Insure (Dogs Only)",
      "url": "https://help.gcash.com/hc/en-us/articles/15553713751065-Malayan-Insurance-Pet-Insure-Dogs-Only"
    },
    {
      "title": "Standard Insurance Pet Health",
      "url": "https://help.gcash.com/hc/en-us/articles/15552480131225-Standard-Insurance-Pet-Health"
    },
    {
      "title": "What are the steps to get a Fully Verified GCash account?",
      "url": "https://help.gcash.com/hc/en-us/articles/360017722393-What-are-the-steps-to-get-a-Fully-Verified-GCash-account"
    },
    {
      "title": "Accepted IDs for GCash Verification",
      "url": "https://help.gcash.com/hc/en-us/articles/900000948786-Accepted-IDs-for-GCash-Verification"
    },
    {
      "title": "How do I send money to another GCash account?",
      "url": "https://help.gcash.com/hc/en-us/articles/360017566614-How-do-I-send-money-to-another-GCash-account"
    },
    {
      "title": "Coverage",
      "url": "https://help.gcash.com/hc/en-us/articles/15553713751065-Malayan-Insurance-Pet-Insure-Dogs-Only#h_01H3BW8R449NC6YWTNXKVFVGGV"
    },
    {
      "title": "Eligibility",
      "url": "https://help.gcash.com/hc/en-us/articles/15553713751065-Malayan-Insurance-Pet-Insure-Dogs-Only#h_01H3BW8WK1MQEKPMTBMCTKX2W2"
    },
    {
      "title": "Purchase Malayan Insurance Pet Insure",
      "url": "https://help.gcash.com/hc/en-us/articles/15553713751065-Malayan-Insurance-Pet-Insure-Dogs-Only#h_01H3BW9616ZFXQ456YWN1B2CS0"
    },
    {
      "title": "Claims",
      "url": "https://help.gcash.com/hc/en-us/articles/15553713751065-Malayan-Insurance-Pet-Insure-Dogs-Only#h_01H3EK7KA5D9QDEMT80M6DDPP5"
    },
    {
      "title": "Cancellation",
      "url": "https://help.gcash.com/hc/en-us/articles/15553713751065-Malayan-Insurance-Pet-Insure-Dogs-Only#h_01H3EK8JMMQVW1WGQGYWVE2NZ3"
    },
    {
      "title": "Contact Malayan Insurance",
      "url": "https://help.gcash.com/hc/en-us/articles/15553713751065-Malayan-Insurance-Pet-Insure-Dogs-Only#h_01H3BW9F2GK57DTCAPM0ET016K"
    },
    {
      "title": "Fully Verified",
      "url": "https://help.gcash.com/hc/en-us/articles/360017722393-How-do-I-get-Fully-Verified-#h_01FPYEDSZ597DXA7JF5NWD6PBC"
    },
    {
      "title": "Previous",
      "url": "https://help.gcash.com/hc/en-us/articles/15553713751065-Malayan-Insurance-Pet-Insure-Dogs-Only#"
    },
    {
      "title": "Next",
      "url": "https://help.gcash.com/hc/en-us/articles/15552480131225-Standard-Insurance-Pet-Health"
    }
  ],
  "images": [
    {
      "alt_text": "How_do_I_apply_for_Pet_Insurance.jpg",
      "url": "https://help.gcash.com/hc/article_attachments/15598909252505"
    }
  ],
  "jump_links": [
    {
      "title": "Coverage",
      "anchor": "https://help.gcash.com/hc/en-us/articles/15553713751065-Malayan-Insurance-Pet-Insure-Dogs-Only#h_01H3BW8R449NC6YWTNXKVFVGGV"
    },
    {
      "title": "Eligibility",
      "anchor": "https://help.gcash.com/hc/en-us/articles/15553713751065-Malayan-Insurance-Pet-Insure-Dogs-Only#h_01H3BW8WK1MQEKPMTBMCTKX2W2"
    },
    {
      "title": "Purchase Malayan Insurance Pet Insure",
      "anchor": "https://help.gcash.com/hc/en-us/articles/15553713751065-Malayan-Insurance-Pet-Insure-Dogs-Only#h_01H3BW9616ZFXQ456YWN1B2CS0"
    },
    {
      "title": "Claims",
      "anchor": "https://help.gcash.com/hc/en-us/articles/15553713751065-Malayan-Insurance-Pet-Insure-Dogs-Only#h_01H3EK7KA5D9QDEMT80M6DDPP5"
    },
    {
      "title": "Cancellation",
      "anchor": "https://help.gcash.com/hc/en-us/articles/15553713751065-Malayan-Insurance-Pet-Insure-Dogs-Only#h_01H3EK8JMMQVW1WGQGYWVE2NZ3"
    },
    {
      "title": "Contact Malayan Insurance",
      "anchor": "https://help.gcash.com/hc/en-us/articles/15553713751065-Malayan-Insurance-Pet-Insure-Dogs-Only#h_01H3BW9F2GK57DTCAPM0ET016K"
    }
  ],
  "description": "Malayan Insurance Pet Insure is an insurance designed for furbabies and pawrents. Pet Insure offers a 3-in-1 package benefit such as...",
  "eligibility": "You can avail of this product if you are:\n\n- 18-65 years old\n- A Filipino or legal resident of the Philippines\n- A [Fully Verified](https://help.gcash.com/hc/en-us/articles/360017722393-How-do-I-get-Fully-Verified-#h_01FPYEDSZ597DXA7JF5NWD6PBC) GCash user\n- An owner of a dog between the age of 6 months and 8 years",
  "coverage": "**Note**: The owner’s liability covers both bodily injury and property damage caused by the insured dog's actions to a third party. This includes liability if the dog bites a non-insured third party.\n\n| **Products Features and Benefits** | **Limits (in PHP)** |\n| --- | --- |\n| **SECTION 1 – MEDICAL REIMBURSEMENT** |\n| Per Occurrence Limit | 30,000.00 |\n| Annual Aggregate Limit | 100,000.00 |\n| Burial Assistance (due to Euthanasia only) | 10,000.00 |\n| Cruciate Ligament Injuries per Leg (Part of MR limit) | 15,000.00 |\n| **SECTION 2 – OWNERS LIABILITY (THIRD PARTY)** |\n| Per Occurrence Limit | 50,000.00 |\n| Annual Aggregate Limit | 250,000.00 |\n| **SECTION 3 – PERSONAL ACCIDENT COVER\\*** |\n| Accidental Death | 50,000.00 |\n| Total Permanent Disability | 50,000.00 |\n| Disablement or Dismemberment | 50,000.00 |\n\n\\*Limit forms part of and not in addition to the Medical Reimbursement limit\n\n\\*\\*Subject to a maximum accumulated limit of PHP 100,000.00 per Insured pet owner with multiple policies.\n\n\\*\\*\\*Subject to schedule of indemnity relative to extent of injury\n\n| **Deductibles** |\n| --- |\n| Section 1 - <br>Medical Reimbursement | PHP 5,000.00 each and every loss<br>Euthanasia Burial Assistance Benefit – NIL |\n| Section 2 –<br>Owner’s Liability | Third Party Bodily Injury – NIL<br>Third Party Property Damage – 5% of loss amount, minimum of<br>PHP 5,000.00, each and every loss |\n| Section 3 – <br>Personal Accident Cover | NIL |\n\n**Note:** Any veterinarian or clinic is acceptable as long as they are properly licensed by the regulatory bodies.\n\nThe policy does not specify which illnesses are covered. Exclusions include:\n\n1. Conditions related to teeth: Dental issues, such as tooth decay or gum disease, are not covered under our Pet insurance policy\n2. Illnesses for which a vaccine is available: Any illness for which a vaccine is readily available, such as rabies or canine parvovirus, falls under the exclusion list\n3. Illnesses related to anal glands: Conditions affecting the anal glands, including anal gland impaction or infection, are not covered by our policy\n4. Illnesses related to behavior: Illnesses or conditions stemming from behavioral issues, such as anxiety-related disorders or compulsive behaviors, are excluded from our coverage\n5. Inherited or Congenital Disease: Diseases or conditions that are inherited or present at birth, such as hip dysplasia or certain heart conditions, fall under this exclusion\n6. Parasite-related diseases: Illnesses caused by parasites, such as fleas, ticks, or heartworm, are not covered by our Pet insurance policy\n7. Specifically excluded diseases: Some specific diseases or conditions may be explicitly excluded from our coverage. Please refer to your policy documentation for a comprehensive list of such exclusions"
}