{
  "article_id": "14465379575193",
  "title": "Standard Insurance Car Protect",
  "url": "https://help.gcash.com/hc/en-us/articles/14465379575193-Standard-Insurance-Car-Protect",
  "content": "#### ADVISORY:\n\nBank Transfer to Maya will be right back! Our partner is working to restore the service as soon as possible.\n\n## Articles in this section\n\n- [BPI MS Compulsory Third Party Liability Insurance](https://help.gcash.com/hc/en-us/articles/6709500387481-BPI-MS-Compulsory-Third-Party-Liability-Insurance)\n- [FPG Insurance Compulsory Third Party Liability (CTPL)](https://help.gcash.com/hc/en-us/articles/10444956195097-FPG-Insurance-Compulsory-Third-Party-Liability-CTPL)\n- [Standard Insurance Car Protect](https://help.gcash.com/hc/en-us/articles/14465379575193-Standard-Insurance-Car-Protect)\n- [Standard Insurance Compulsory Third Party Liability (CTPL)](https://help.gcash.com/hc/en-us/articles/14464629819161-Standard-Insurance-Compulsory-Third-Party-Liability-CTPL)\n\n## Promoted articles\n\n- [What are the steps to get a Fully Verified GCash account?](https://help.gcash.com/hc/en-us/articles/360017722393-What-are-the-steps-to-get-a-Fully-Verified-GCash-account)\n- [Accepted IDs for GCash Verification](https://help.gcash.com/hc/en-us/articles/900000948786-Accepted-IDs-for-GCash-Verification)\n- [How do I send money to another GCash account?](https://help.gcash.com/hc/en-us/articles/360017566614-How-do-I-send-money-to-another-GCash-account)\n\nStandard Insurance Car Protect is a comprehensive motorcar insurance that protects your vehicle from losses arising from accidents, theft, and acts of nature (optional). Car Protect was designed exclusively for four-wheeled private-use vehicles including sedans, SUVs, AUVs, vans, station wagons, and pickups.\n\nJump to:\n\n- [Eligibility](https://help.gcash.com/hc/en-us/articles/14465379575193-Standard-Insurance-Car-Protect#h_01H5S7T6C4V9VX8PFSBZJ0NEKG)\n- [Benefits](https://help.gcash.com/hc/en-us/articles/14465379575193-Standard-Insurance-Car-Protect#h_01GPJR9TFQ2V7S39J7P9AVT106)\n- [Purchase Car Protect by Standard Insurance](https://help.gcash.com/hc/en-us/articles/14465379575193-Standard-Insurance-Car-Protect#h_01GPJR8M0GR9EZGT2BH8P5HR2D)  - [View policy contract](https://help.gcash.com/hc/en-us/articles/14465379575193-Standard-Insurance-Car-Protect#h_01H5S8C4JQE2F1YW4W6KT2DTDZ)\n  - [Changes in policy](https://help.gcash.com/hc/en-us/articles/14465379575193-Standard-Insurance-Car-Protect#h_01H5S8C9FKV5QVHNR8XZPKZH7G)\n  - [Insurance transfer](https://help.gcash.com/hc/en-us/articles/14465379575193-Standard-Insurance-Car-Protect#h_01H5S8CKBBWP1RNVGXSST2J9GF)\n- [Claims](https://help.gcash.com/hc/en-us/articles/14465379575193-Standard-Insurance-Car-Protect#h_01GPJR8ZXQP4S614VB5AXRBAHV)\n- [Renewal, Refund and Cancellation](https://help.gcash.com/hc/en-us/articles/14465379575193-Standard-Insurance-Car-Protect#h_01H4JHF6RHCPCRVZAX206733FK)\n\n## Eligibility\n\nYou can avail of this product if you are:\n\n- A [Fully Verified](https://help.gcash.com/hc/en-us/articles/360017722393-Get-Fully-Verified) GCash user\n- The owner of a car that can be insured\n\nRequirements for the car:\n\n- Private Cars: Sedan, AUV, MPV, Wagon, Van, Pick-up\n- Age of car up to 15 years old\n- Usage must be private\n\n**Note:** You may also purchase Car Protect by Standard Insurance on behalf of someone else.\n\n## Benefits\n\nCar Protect by Standard Insurance has comprehensive coverage that responds in cases where the insured's vehicle is damaged, the insured or its passengers are injured, the insured's vehicle caused damage to the property of others, and if the insured's vehicle injured other people.\n\n| **Compulsory Third Party Liability (CTPL)** |\n| --- |\n| Covers Bodily injury and/or death caused to a Third Party (person/s) by the Assured; required by law upon vehicle registration. Standard Insurance will settle a valid claim of up to PHP 100,000, subject to the policy limits. This is purchased separately. |\n\n| **Comprehensive Insurance** |\n| --- |\n| **Own Damage and Theft (OD/Th)** | Covers accidental collision, overturning, falling, fire, and malicious acts of a Third Party on the assured’s vehicle; Standard Insurance will settle a valid claim of up to the Sum Insured. |\n| **Voluntary Third Party Bodily Injury (VTPBI)** | Responds in excess of the Assured’s CTPL insurance in respect of bodily injury and/or death caused to a Third Party (person/s) by the Assured. Standard Insurance will settle a valid claim of up to the sum insured, over and above the PhP100,000 covered by the Assured’s CTPL insurance. |\n| **Voluntary Third Party Property Damage (VTPPD)** | Covers damage to property owned by one or more third parties, arising from an accident caused by the Assured’s vehicle. Standard Insurance will settle a valid claim of up the sum insured. |\n| **·Personal Accident (PA) Rider (Auto PA)** | Covers Medical treatment, dismemberment, permanent disability and/or death arising from bodily injuries caused by an external accident while the Assured or an authorized driver or any of the vehicle’s passengers are riding in, boarding or alighting from the insured vehicle. Standard Insurance will settle a valid claim of up to PhP100,000 per person, up to its maximum legal seating capacity. |\n| **Acts of Nature (AON)** | Covers direct loss of, or damage to, the insured vehicle, its accessories and spare parts caused by an earthquake, typhoon, flood, volcanic eruption, lightning, fire and/or other convulsions of nature; Standard Insurance will settle a valid claim of up to the Sum Insured. |\n| **Roadside Assistance** | Provides free towing service, battery boosting, locksmith, personal assistance up to the limit specified. |\n\n## Purchase Car Protect by Standard Insurance\n\nThe amount for the annual premium payment will be automatically deducted from your GCash wallet upon purchase. Please make sure you have enough balance in your GCash wallet to make a successful transaction\n\nYou can avail as many car insurance policies as you can depending on the number of cars that you own.\n\n![How_to_purchase_Car_Protect_by_Standard_Insurance.jpg](https://help.gcash.com/hc/article_attachments/14465220365337)\n\nYou will receive a confirmation SMS and an email of your Car Protect Policy.\n\n### **View Policy Contract**\n\nYour Policy Contract and other Policy documents are sent to your registered email address within an hour of your successful purchase. If you were not able to receive your policy within 24 hours or if you would like to request an original copy of your policy, please [contact Standard Insurance](https://help.gcash.com/hc/en-us/articles/14465379575193-Standard-Insurance-Car-Protect#h_01H5S89JWFFDN6EG58VRV5P0RG).\n\n### **Changes in policy**\n\nIf you have any changes in your policy, please [contact Standard Insurance](https://help.gcash.com/hc/en-us/articles/14465379575193-Standard-Insurance-Car-Protect#h_01H5S89JWFFDN6EG58VRV5P0RG).\n\n**Note:** Any change or modification in your insured vehicle (i.e. engine no., color, etc.) must be declared in the policy.  New details that may be found contrary to the policy that are not properly endorsed may be used as grounds for the denial of the claim.\n\n### **Insurance transfer**\n\nYou can transfer the Car Protect policy if you plan to sell your vehicle provided that you secure the approval of the Insurer by [contacting Standard Insurance](https://help.gcash.com/hc/en-us/articles/14465379575193-Standard-Insurance-Car-Protect#h_01H5S89JWFFDN6EG58VRV5P0RG). Please make sure that the policy is endorsed to reflect the new owner of the insured vehicle.\n\n## Claims\n\nYou can file a claim for loss or damage immediately after the occurrence or up to 60 days. For Acts of Nature claims, you must file your claim within seven (7) days from the date of the typhoon, flood, earthquake, flood, or other convulsions of nature.\n\nTo file a claim, go to the [Standard Insurance Online Claims Notification](https://bit.ly/OnlineClaimNotification). Once you have completed the form and have attached the required documents, a representative from Standard Insurance will email you the next steps necessary to process your claim. You may [contact Standard Insurance](https://help.gcash.com/hc/en-us/articles/14465379575193-Standard-Insurance-Car-Protect#h_01H5S89JWFFDN6EG58VRV5P0RG) to follow up.\n\n### **Requirements for claiming the policy**\n\nTo file a claim for your Car Protect Policy, please prepare the following documents:\n\n- Certificate of Registration (CR) and Official Receipt (OR) or Certificate of Registration covering loss date\n- Driver’s license\n- Affidavit or police report (if with third party)\n- Photos showing the full body of the vehicle that include the plate number/conductions sticker or VIN plate, damages on the unit, and odometer reading.\n- Letter of Authority Issued to CASA/Repair Shop or Cash Settlement\n\nOnce you have filed a claim and have completed the required documents, it will be processed within 5 days for claims up to PHP 100,000 and 5-20 days for other cases depending on the extent of the damage.\n\n## Renewal, Refund, and Cancellation\n\n### **Renewal**\n\nTo renew your policy, please register your existing policy for online access on the [Standard Insurance website](https://bit.ly/MyStandardOnline). Registered policies get a renewal prompt 90 days before policy expiration. You may log in to your online access to initiate a renewal or you may [contact Standard Insurance](https://help.gcash.com/hc/en-us/articles/14465379575193-Standard-Insurance-Car-Protect#h_01H5S89JWFFDN6EG58VRV5P0RG).\n\n### **Refund**\n\nYou may request a refund and cancel your policy **within seven (7) days after receiving it via email**. All premiums shall be returned to your GCash wallet provided it is made before 12:00 AM (midnight) of the same day of purchase. A representative of Standard Insurance shall process cancellation requests made after the cut-off. Refund shall be credited back to your GCash wallet or nominated bank account.\n\nIf the 7-day cancellation period falls on the following month, pro-rata premium and taxes shall be returned except the documentary stamps.\n\n### **Cancellation**\n\nYou may request the cancellation of your policy if your unit has been sold. If you did not file a claim during the policy year, a refund on the basic premium, excluding taxes, will be processed based on the Short Period Rate Scale stipulated in your policy.  However, if you have already incurred a claim and collected the proceeds or in process before your request for cancellation, no premium and taxes will be returned.\n\n## Contact Standard Insurance\n\nTo contact Standard Insurance, please check out their available channels below:\n\n**Mobile**: (+63)917-828-3984 from 8:00 AM-5:00 PM\n\n**Hotline**: (+632) 8845-1111 after 5:00 PM\n\n**Facebook**: @StandardInsurancePH\n\n**Email**: [inquiry@standard-insurance.com](mailto:inquiry@standard-insurance.com)\n\n[Previous](https://help.gcash.com/hc/en-us/articles/10444956195097-FPG-Insurance-Compulsory-Third-Party-Liability-CTPL)\n\nFPG Insurance Compulsory Third Party Liability (CTPL)\n\n[Next](https://help.gcash.com/hc/en-us/articles/14464629819161-Standard-Insurance-Compulsory-Third-Party-Liability-CTPL)\n\nStandard Insurance Compulsory Third Party Liability (CTPL)\n\n- [BPI MS Compulsory Third Party Liability Insurance](https://help.gcash.com/hc/en-us/articles/6709500387481-BPI-MS-Compulsory-Third-Party-Liability-Insurance)\n- [FPG Insurance Compulsory Third Party Liability (CTPL)](https://help.gcash.com/hc/en-us/articles/10444956195097-FPG-Insurance-Compulsory-Third-Party-Liability-CTPL)\n- [Standard Insurance Car Protect](https://help.gcash.com/hc/en-us/articles/14465379575193-Standard-Insurance-Car-Protect)\n- [Standard Insurance Compulsory Third Party Liability (CTPL)](https://help.gcash.com/hc/en-us/articles/14464629819161-Standard-Insurance-Compulsory-Third-Party-Liability-CTPL)\n\n14465379575193\n\nBack to Top",
  "categories": [
    "BPI MS Compulsory Third Party Liability Insurance",
    "FPG Insurance Compulsory Third Party Liability (CTPL)",
    "Standard Insurance Car Protect",
    "Standard Insurance Compulsory Third Party Liability (CTPL)"
  ],
  "related_articles": [
    {
      "title": "BPI MS Compulsory Third Party Liability Insurance",
      "url": "https://help.gcash.com/hc/en-us/articles/6709500387481-BPI-MS-Compulsory-Third-Party-Liability-Insurance"
    },
    {
      "title": "FPG Insurance Compulsory Third Party Liability (CTPL)",
      "url": "https://help.gcash.com/hc/en-us/articles/10444956195097-FPG-Insurance-Compulsory-Third-Party-Liability-CTPL"
    },
    {
      "title": "Standard Insurance Car Protect",
      "url": "https://help.gcash.com/hc/en-us/articles/14465379575193-Standard-Insurance-Car-Protect"
    },
    {
      "title": "Standard Insurance Compulsory Third Party Liability (CTPL)",
      "url": "https://help.gcash.com/hc/en-us/articles/14464629819161-Standard-Insurance-Compulsory-Third-Party-Liability-CTPL"
    },
    {
      "title": "What are the steps to get a Fully Verified GCash account?",
      "url": "https://help.gcash.com/hc/en-us/articles/360017722393-What-are-the-steps-to-get-a-Fully-Verified-GCash-account"
    },
    {
      "title": "Accepted IDs for GCash Verification",
      "url": "https://help.gcash.com/hc/en-us/articles/900000948786-Accepted-IDs-for-GCash-Verification"
    },
    {
      "title": "How do I send money to another GCash account?",
      "url": "https://help.gcash.com/hc/en-us/articles/360017566614-How-do-I-send-money-to-another-GCash-account"
    },
    {
      "title": "Eligibility",
      "url": "https://help.gcash.com/hc/en-us/articles/14465379575193-Standard-Insurance-Car-Protect#h_01H5S7T6C4V9VX8PFSBZJ0NEKG"
    },
    {
      "title": "Benefits",
      "url": "https://help.gcash.com/hc/en-us/articles/14465379575193-Standard-Insurance-Car-Protect#h_01GPJR9TFQ2V7S39J7P9AVT106"
    },
    {
      "title": "Purchase Car Protect by Standard Insurance",
      "url": "https://help.gcash.com/hc/en-us/articles/14465379575193-Standard-Insurance-Car-Protect#h_01GPJR8M0GR9EZGT2BH8P5HR2D"
    },
    {
      "title": "View policy contract",
      "url": "https://help.gcash.com/hc/en-us/articles/14465379575193-Standard-Insurance-Car-Protect#h_01H5S8C4JQE2F1YW4W6KT2DTDZ"
    },
    {
      "title": "Changes in policy",
      "url": "https://help.gcash.com/hc/en-us/articles/14465379575193-Standard-Insurance-Car-Protect#h_01H5S8C9FKV5QVHNR8XZPKZH7G"
    },
    {
      "title": "Insurance transfer",
      "url": "https://help.gcash.com/hc/en-us/articles/14465379575193-Standard-Insurance-Car-Protect#h_01H5S8CKBBWP1RNVGXSST2J9GF"
    },
    {
      "title": "Claims",
      "url": "https://help.gcash.com/hc/en-us/articles/14465379575193-Standard-Insurance-Car-Protect#h_01GPJR8ZXQP4S614VB5AXRBAHV"
    },
    {
      "title": "Renewal, Refund and Cancellation",
      "url": "https://help.gcash.com/hc/en-us/articles/14465379575193-Standard-Insurance-Car-Protect#h_01H4JHF6RHCPCRVZAX206733FK"
    },
    {
      "title": "Fully Verified",
      "url": "https://help.gcash.com/hc/en-us/articles/360017722393-Get-Fully-Verified"
    },
    {
      "title": "contact Standard Insurance",
      "url": "https://help.gcash.com/hc/en-us/articles/14465379575193-Standard-Insurance-Car-Protect#h_01H5S89JWFFDN6EG58VRV5P0RG"
    },
    {
      "title": "contacting Standard Insurance",
      "url": "https://help.gcash.com/hc/en-us/articles/14465379575193-Standard-Insurance-Car-Protect#h_01H5S89JWFFDN6EG58VRV5P0RG"
    },
    {
      "title": "Standard Insurance Online Claims Notification](https://bit.ly/OnlineClaimNotification). Once you have completed the form and have attached the required documents, a representative from Standard Insurance will email you the next steps necessary to process your claim. You may [contact Standard Insurance",
      "url": "https://help.gcash.com/hc/en-us/articles/14465379575193-Standard-Insurance-Car-Protect#h_01H5S89JWFFDN6EG58VRV5P0RG"
    },
    {
      "title": "Standard Insurance website](https://bit.ly/MyStandardOnline). Registered policies get a renewal prompt 90 days before policy expiration. You may log in to your online access to initiate a renewal or you may [contact Standard Insurance",
      "url": "https://help.gcash.com/hc/en-us/articles/14465379575193-Standard-Insurance-Car-Protect#h_01H5S89JWFFDN6EG58VRV5P0RG"
    },
    {
      "title": "Previous",
      "url": "https://help.gcash.com/hc/en-us/articles/10444956195097-FPG-Insurance-Compulsory-Third-Party-Liability-CTPL"
    },
    {
      "title": "Next",
      "url": "https://help.gcash.com/hc/en-us/articles/14464629819161-Standard-Insurance-Compulsory-Third-Party-Liability-CTPL"
    }
  ],
  "images": [
    {
      "alt_text": "How_to_purchase_Car_Protect_by_Standard_Insurance.jpg",
      "url": "https://help.gcash.com/hc/article_attachments/14465220365337"
    }
  ],
  "jump_links": [
    {
      "title": "Eligibility",
      "anchor": "https://help.gcash.com/hc/en-us/articles/14465379575193-Standard-Insurance-Car-Protect#h_01H5S7T6C4V9VX8PFSBZJ0NEKG"
    },
    {
      "title": "Benefits",
      "anchor": "https://help.gcash.com/hc/en-us/articles/14465379575193-Standard-Insurance-Car-Protect#h_01GPJR9TFQ2V7S39J7P9AVT106"
    },
    {
      "title": "Purchase Car Protect by Standard Insurance",
      "anchor": "https://help.gcash.com/hc/en-us/articles/14465379575193-Standard-Insurance-Car-Protect#h_01GPJR8M0GR9EZGT2BH8P5HR2D"
    },
    {
      "title": "Changes in policy",
      "anchor": "https://help.gcash.com/hc/en-us/articles/14465379575193-Standard-Insurance-Car-Protect#h_01H5S8C9FKV5QVHNR8XZPKZH7G"
    },
    {
      "title": "Insurance transfer",
      "anchor": "https://help.gcash.com/hc/en-us/articles/14465379575193-Standard-Insurance-Car-Protect#h_01H5S8CKBBWP1RNVGXSST2J9GF"
    },
    {
      "title": "Claims",
      "anchor": "https://help.gcash.com/hc/en-us/articles/14465379575193-Standard-Insurance-Car-Protect#h_01GPJR8ZXQP4S614VB5AXRBAHV"
    },
    {
      "title": "Renewal, Refund and Cancellation",
      "anchor": "https://help.gcash.com/hc/en-us/articles/14465379575193-Standard-Insurance-Car-Protect#h_01H4JHF6RHCPCRVZAX206733FK"
    }
  ],
  "description": "Standard Insurance Car Protect is a comprehensive motorcar insurance that protects your vehicle from losses arising from accidents,...",
  "eligibility": "You can avail of this product if you are:\n\n- A [Fully Verified](https://help.gcash.com/hc/en-us/articles/360017722393-Get-Fully-Verified) GCash user\n- The owner of a car that can be insured\n\nRequirements for the car:\n\n- Private Cars: Sedan, AUV, MPV, Wagon, Van, Pick-up\n- Age of car up to 15 years old\n- Usage must be private\n\n**Note:** You may also purchase Car Protect by Standard Insurance on behalf of someone else."
}