{
  "article_id": "4405429296665",
  "title": "GInsure Bill Protect",
  "url": "https://help.gcash.com/hc/en-us/articles/4405429296665-GInsure-Bill-Protect",
  "content": "#### ADVISORY:\n\nBank Transfer to Maya will be right back! Our partner is working to restore the service as soon as possible.\n\n## Articles in this section\n\n- [Cebuana Lhuillier Personal Accident Basic Insurance Program](https://help.gcash.com/hc/en-us/articles/13923921923097-Cebuana-Lhuillier-Personal-Accident-Basic-Insurance-Program)\n- [FPG Insurance Personal Accident Protection](https://help.gcash.com/hc/en-us/articles/14836639630489-FPG-Insurance-Personal-Accident-Protection)\n- [GInsure Bill Protect](https://help.gcash.com/hc/en-us/articles/4405429296665-GInsure-Bill-Protect)\n- [Pru Life UK PRUPersonal Accident](https://help.gcash.com/hc/en-us/articles/11266780762265-Pru-Life-UK-PRUPersonal-Accident)\n- [Pru Life UK PRUPersonal Accident – Junior Protect](https://help.gcash.com/hc/en-us/articles/9535701684761-Pru-Life-UK-PRUPersonal-Accident-Junior-Protect)\n- [Singlife Cash for Income Loss due to Accidents](https://help.gcash.com/hc/en-us/articles/900005482606-Singlife-Cash-for-Income-Loss-due-to-Accidents)\n\n## Promoted articles\n\n- [What are the steps to get a Fully Verified GCash account?](https://help.gcash.com/hc/en-us/articles/360017722393-What-are-the-steps-to-get-a-Fully-Verified-GCash-account)\n- [Accepted IDs for GCash Verification](https://help.gcash.com/hc/en-us/articles/900000948786-Accepted-IDs-for-GCash-Verification)\n- [How do I send money to another GCash account?](https://help.gcash.com/hc/en-us/articles/360017566614-How-do-I-send-money-to-another-GCash-account)\n\nGInsure Bill Protect is an insurance that covers you when you are unable to earn and settle your payment obligations in case of accidental death and permanent disablement.\n\nThe Group Policy pays out a lump sum benefit which covers up to 36 months (3 years) of the GCash bill payment amount at the time of enrollment.\n\nJump to:\n\n- [Eligibility](https://help.gcash.com/hc/en-us/articles/4405429296665-GInsure-Bill-Protect#h_01H51R3V3QWNJQ4EYKM4PFZXND)\n- [Coverage and Benefits](https://help.gcash.com/hc/en-us/articles/4405429296665-GInsure-Bill-Protect#h_01H51RZ4QBX91WDNERAPA10APK)\n- [Enrollment and Payment](https://help.gcash.com/hc/en-us/articles/4405429296665-GInsure-Bill-Protect#h_01H51RHDZ8G2X94JTSAE330R1M)\n- [Claims and Cancellation](https://help.gcash.com/hc/en-us/articles/4405429296665-GInsure-Bill-Protect#h_01H51R3FGM8VX1PNVHG28RD5WY)\n- [Contact Chubb](https://help.gcash.com/hc/en-us/articles/4405429296665-GInsure-Bill-Protect#h_01J2K1B3YHXJ75WJEEHEGJK0BS)\n\n## Eligibility\n\nYou can enroll in GInsure Bill Protect if you fulfill all of the requirements below:\n\n- At least 18-75 years old\n- A Filipino or legal Philippine resident\n- Have a GCash account\n- Paid a biller in Pay Bills via GCash app\n\n## Coverage and Benefits\n\n### **Coverage**\n\nAll biller categories are eligible for GInsure Bill Protect. You will be covered for **thirty (30) calendar days**, effective on the day of your successful GCash Pay Bills transaction with enrollment to GInsure Bill Protect, after which coverage will end.\n\n| Bill Payment Transaction Date | Insurance Coverage Period |\n| --- | --- |\n| November 1, 2019 | November 1 - 30, 2019 |\n\nThe following are **not covered** under GInsure Bill Protect - Accidental Death and Permanent Disablement arising from:\n\n- Self-inflicted injury\n- Suicide\n- Criminal or illegal act\n- Being under the influence of alcohol or unprescribed drugs\n- HIV/AIDS-related\n- Conditions arising from abortion, pregnancy, childbirth, or miscarriage\n\nYou may enroll a bill and pay the premium again when you make another GCash bill payment, upon which your coverage will reset for another calendar month. The more bills paid and enrolled under GInsure Bill Protect, the bigger the lump sum benefit amount will be under the covered period.\n\n### **Benefits**\n\nYou will be covered **36 times the GCash bill amount paid** if you are unable to earn and settle your payment obligations due to accidental death and permanent disablement.\n\nSample computation of total benefit:\n\n- Bill Payment Amount: PHP 1,500 x 36 months = PHP 54,000 coverage\n\nThe benefit is payable to the GCash account owner who successfully paid a bill and GInsure Bill Protect premium via GCash. It may not be the same individual whose name is reflected on the bill.\n\nIn case of the insured’s death, it will be payable to the beneficiary designated by the insured, or in the absence of beneficiary designation, to the person or persons in the following order of preference:\n\n- Legal spouse\n- Children\n- Parents\n- Siblings\n\n**Example**: John pays for his father’s bill via his GCash account and enrolls it in GInsure Bill Protect. John is the Insured.\n\n## Enrollment and Payment\n\n### **Enrollment**\n\nYou can enroll a bill to GInsure Bill Protect as an add-on every time you make a Pay Bills transaction via the GCash app. You can also enroll more than one because the more bills paid and enrolled with GInsure Bill Protect, the bigger the lump sum benefit amount will be under the covered period.\n\n![mceclip2.png](https://help.gcash.com/hc/article_attachments/4405429243289)\n\nYou will receive a **Confirmation of Cover** from our insurance partner, Chubb, within **24-48 hours** after successful enrolment to GInsure Bill Protect as part of your transaction.\n\nYou can also visit the MyGInsure page in the GCash app to check your policies.\n\n- Select GInsure > select My GInsure and under > Active Policies select your Bill Protect policy. Take note of your policy number.\n- Visit Chubb MyAccount and log in using your policy number and the OTP received via SMS or email. Click \"Download\" under Policy Details to download a copy of your Confirmation of Cover.\n\n### **Payment**\n\n**Note:** Payment\n\nThe premium is computed as Bill Payment Amount x 0.920%.\n\n| **Sample computation of GInsure Bill Protect Premium** |\n| --- |\n| Sample GCash Bill Payment Amount - Ex. Meralco | PHP 1,500.00 |\n| \\+ Premium to be added upon checkout (0.920% of bill payment) | PHP 13.80 |\n| Total Payment at checkout | PHP 1,513.80 |\n\n**Note**: GCash has a maximum total transaction amount per fully verifieduser, which is PHP 100,000 per month. Cap for the insurable amount will follow the same limits.\n\nThe lump sum benefit cap will hence be: PHP 100,000 x 36 months = PHP 3,600,000\n\n## Claims and Cancellation\n\n### **Claims**\n\nTo file a claim, prepare the following requirements:\n\n1. Valid ID of the Insured (GCash User) or of the Beneficiary of the GCash User\n2. Birth & Death Certificates of the Insured\n3. Proof of Relationship to Beneficiary\n4. Attending Physician’s Report\n5. Original Copy of Police Report\n6. Notarized Affidavit of Witness\n7. Autopsy Report or Medico-Legal Statement\n\n\n**Then, visit the Chubb Claims Centre at [www.chubbclaims.com.ph](http://www.chubbclaims.com.ph/) and submit your claim from anywhere and on any device. You will also have real-time access to the status of your claims.**\n\n### **Cancellation**\n\nYou can request cancellation of your cover during the free-look period which is **within 7 days** from the time of successful Pay Bills transaction with enrollment to GInsure Bill Protect. The premium will be refunded to your GCash wallet in full within this period.\n\nIf you would like to cancel Bill Protect, please tap \"Chat with Gigi\" for assistance.\n\n## Contact Chubb\n\nIf you have questions about your policy, filing of claims, or status of claims filed:\n\n- You may call the Chubb hotline +63277565410, Monday to Friday, 9:00am – 5:00pm, excluding public holidays.\n\nYou may also email [gcashcustomerinquiries@chubb.com](mailto:gcashcustomerinquiries@chubb.com)\n\n[Previous](https://help.gcash.com/hc/en-us/articles/14836639630489-FPG-Insurance-Personal-Accident-Protection)\n\nFPG Insurance Personal Accident Protection\n\n[Next](https://help.gcash.com/hc/en-us/articles/11266780762265-Pru-Life-UK-PRUPersonal-Accident)\n\nPru Life UK PRUPersonal Accident\n\n- [Cebuana Lhuillier Personal Accident Basic Insurance Program](https://help.gcash.com/hc/en-us/articles/13923921923097-Cebuana-Lhuillier-Personal-Accident-Basic-Insurance-Program)\n- [FPG Insurance Personal Accident Protection](https://help.gcash.com/hc/en-us/articles/14836639630489-FPG-Insurance-Personal-Accident-Protection)\n- [GInsure Bill Protect](https://help.gcash.com/hc/en-us/articles/4405429296665-GInsure-Bill-Protect)\n- [Pru Life UK PRUPersonal Accident](https://help.gcash.com/hc/en-us/articles/11266780762265-Pru-Life-UK-PRUPersonal-Accident)\n- [Pru Life UK PRUPersonal Accident – Junior Protect](https://help.gcash.com/hc/en-us/articles/9535701684761-Pru-Life-UK-PRUPersonal-Accident-Junior-Protect)\n- [Singlife Cash for Income Loss due to Accidents](https://help.gcash.com/hc/en-us/articles/900005482606-Singlife-Cash-for-Income-Loss-due-to-Accidents)\n\n4405429296665\n\nBack to Top\n\n[iframe](https://gcash.ada.support/embed/x-storage/2d26b66/index.html)[iframe](https://gcash.ada.support/embed/button/2d26b66/index.html)[iframe](https://gcash.ada.support/embed/intro/2d26b66/index.html)",
  "categories": [
    "Cebuana Lhuillier Personal Accident Basic Insurance Program",
    "FPG Insurance Personal Accident Protection",
    "GInsure Bill Protect",
    "Pru Life UK PRUPersonal Accident",
    "Pru Life UK PRUPersonal Accident – Junior Protect",
    "Singlife Cash for Income Loss due to Accidents"
  ],
  "related_articles": [
    {
      "title": "Cebuana Lhuillier Personal Accident Basic Insurance Program",
      "url": "https://help.gcash.com/hc/en-us/articles/13923921923097-Cebuana-Lhuillier-Personal-Accident-Basic-Insurance-Program"
    },
    {
      "title": "FPG Insurance Personal Accident Protection",
      "url": "https://help.gcash.com/hc/en-us/articles/14836639630489-FPG-Insurance-Personal-Accident-Protection"
    },
    {
      "title": "GInsure Bill Protect",
      "url": "https://help.gcash.com/hc/en-us/articles/4405429296665-GInsure-Bill-Protect"
    },
    {
      "title": "Pru Life UK PRUPersonal Accident",
      "url": "https://help.gcash.com/hc/en-us/articles/11266780762265-Pru-Life-UK-PRUPersonal-Accident"
    },
    {
      "title": "Pru Life UK PRUPersonal Accident – Junior Protect",
      "url": "https://help.gcash.com/hc/en-us/articles/9535701684761-Pru-Life-UK-PRUPersonal-Accident-Junior-Protect"
    },
    {
      "title": "Singlife Cash for Income Loss due to Accidents",
      "url": "https://help.gcash.com/hc/en-us/articles/900005482606-Singlife-Cash-for-Income-Loss-due-to-Accidents"
    },
    {
      "title": "What are the steps to get a Fully Verified GCash account?",
      "url": "https://help.gcash.com/hc/en-us/articles/360017722393-What-are-the-steps-to-get-a-Fully-Verified-GCash-account"
    },
    {
      "title": "Accepted IDs for GCash Verification",
      "url": "https://help.gcash.com/hc/en-us/articles/900000948786-Accepted-IDs-for-GCash-Verification"
    },
    {
      "title": "How do I send money to another GCash account?",
      "url": "https://help.gcash.com/hc/en-us/articles/360017566614-How-do-I-send-money-to-another-GCash-account"
    },
    {
      "title": "Eligibility",
      "url": "https://help.gcash.com/hc/en-us/articles/4405429296665-GInsure-Bill-Protect#h_01H51R3V3QWNJQ4EYKM4PFZXND"
    },
    {
      "title": "Coverage and Benefits",
      "url": "https://help.gcash.com/hc/en-us/articles/4405429296665-GInsure-Bill-Protect#h_01H51RZ4QBX91WDNERAPA10APK"
    },
    {
      "title": "Enrollment and Payment",
      "url": "https://help.gcash.com/hc/en-us/articles/4405429296665-GInsure-Bill-Protect#h_01H51RHDZ8G2X94JTSAE330R1M"
    },
    {
      "title": "Claims and Cancellation",
      "url": "https://help.gcash.com/hc/en-us/articles/4405429296665-GInsure-Bill-Protect#h_01H51R3FGM8VX1PNVHG28RD5WY"
    },
    {
      "title": "Contact Chubb",
      "url": "https://help.gcash.com/hc/en-us/articles/4405429296665-GInsure-Bill-Protect#h_01J2K1B3YHXJ75WJEEHEGJK0BS"
    },
    {
      "title": "Previous",
      "url": "https://help.gcash.com/hc/en-us/articles/14836639630489-FPG-Insurance-Personal-Accident-Protection"
    },
    {
      "title": "Next",
      "url": "https://help.gcash.com/hc/en-us/articles/11266780762265-Pru-Life-UK-PRUPersonal-Accident"
    }
  ],
  "images": [
    {
      "alt_text": "mceclip2.png",
      "url": "https://help.gcash.com/hc/article_attachments/4405429243289"
    }
  ],
  "jump_links": [
    {
      "title": "Eligibility",
      "anchor": "https://help.gcash.com/hc/en-us/articles/4405429296665-GInsure-Bill-Protect#h_01H51R3V3QWNJQ4EYKM4PFZXND"
    },
    {
      "title": "Coverage and Benefits",
      "anchor": "https://help.gcash.com/hc/en-us/articles/4405429296665-GInsure-Bill-Protect#h_01H51RZ4QBX91WDNERAPA10APK"
    },
    {
      "title": "Enrollment and Payment",
      "anchor": "https://help.gcash.com/hc/en-us/articles/4405429296665-GInsure-Bill-Protect#h_01H51RHDZ8G2X94JTSAE330R1M"
    },
    {
      "title": "Claims and Cancellation",
      "anchor": "https://help.gcash.com/hc/en-us/articles/4405429296665-GInsure-Bill-Protect#h_01H51R3FGM8VX1PNVHG28RD5WY"
    },
    {
      "title": "Contact Chubb",
      "anchor": "https://help.gcash.com/hc/en-us/articles/4405429296665-GInsure-Bill-Protect#h_01J2K1B3YHXJ75WJEEHEGJK0BS"
    }
  ],
  "description": "GInsure Bill Protect is an insurance that covers you when you are unable to earn and settle your payment obligations in case of...",
  "product_tables": [
    "| Bill Payment Transaction Date | Insurance Coverage Period |\n| --- |",
    "|\n| November 1, 2019 | November 1 - 30, 2019 |\n\nThe following are **not covered** under GInsure Bill Protect - Accidental Death and Permanent Disablement arising from:\n\n- Self-inflicted injury\n- Suicide\n- Criminal or illegal act\n- Being under the influence of alcohol or unprescribed drugs\n- HIV/AIDS-related\n- Conditions arising from abortion, pregnancy, childbirth, or miscarriage\n\nYou may enroll a bill and pay the premium again when you make another GCash bill payment, upon which your coverage will reset for another calendar month. The more bills paid and enrolled under GInsure Bill Protect, the bigger the lump sum benefit amount will be under the covered period.\n\n### **Benefits**\n\nYou will be covered **36 times the GCash bill amount paid** if you are unable to earn and settle your payment obligations due to accidental death and permanent disablement.\n\nSample computation of total benefit:\n\n- Bill Payment Amount: PHP 1,500 x 36 months = PHP 54,000 coverage\n\nThe benefit is payable to the GCash account owner who successfully paid a bill and GInsure Bill Protect premium via GCash. It may not be the same individual whose name is reflected on the bill.\n\nIn case of the insured’s death, it will be payable to the beneficiary designated by the insured, or in the absence of beneficiary designation, to the person or persons in the following order of preference:\n\n- Legal spouse\n- Children\n- Parents\n- Siblings\n\n**Example**: John pays for his father’s bill via his GCash account and enrolls it in GInsure Bill Protect. John is the Insured.\n\n## Enrollment and Payment\n\n### **Enrollment**\n\nYou can enroll a bill to GInsure Bill Protect as an add-on every time you make a Pay Bills transaction via the GCash app. You can also enroll more than one because the more bills paid and enrolled with GInsure Bill Protect, the bigger the lump sum benefit amount will be under the covered period.\n\n![mceclip2.png](https://help.gcash.com/hc/article_attachments/4405429243289)\n\nYou will receive a **Confirmation of Cover** from our insurance partner, Chubb, within **24-48 hours** after successful enrolment to GInsure Bill Protect as part of your transaction.\n\nYou can also visit the MyGInsure page in the GCash app to check your policies.\n\n- Select GInsure > select My GInsure and under > Active Policies select your Bill Protect policy. Take note of your policy number.\n- Visit Chubb MyAccount and log in using your policy number and the OTP received via SMS or email. Click \"Download\" under Policy Details to download a copy of your Confirmation of Cover.\n\n### **Payment**\n\n**Note:** Payment\n\nThe premium is computed as Bill Payment Amount x 0.920%.\n\n| **Sample computation of GInsure Bill Protect Premium** |\n| --- |\n| Sample GCash Bill Payment Amount - Ex. Meralco |",
    "|\n| \\+ Premium to be added upon checkout (0.920% of bill payment) | PHP 13.80 |\n| Total Payment at checkout |"
  ],
  "eligibility": "You can enroll in GInsure Bill Protect if you fulfill all of the requirements below:\n\n- At least 18-75 years old\n- A Filipino or legal Philippine resident\n- Have a GCash account\n- Paid a biller in Pay Bills via GCash app"
}