{
  "article_id": "14464629819161",
  "title": "Standard Insurance Compulsory Third Party Liability (CTPL)",
  "url": "https://help.gcash.com/hc/en-us/articles/14464629819161-Standard-Insurance-Compulsory-Third-Party-Liability-CTPL",
  "content": "#### ADVISORY:\n\nBank Transfer to Maya will be right back! Our partner is working to restore the service as soon as possible.\n\n## Articles in this section\n\n- [BPI MS Compulsory Third Party Liability Insurance](https://help.gcash.com/hc/en-us/articles/6709500387481-BPI-MS-Compulsory-Third-Party-Liability-Insurance)\n- [FPG Insurance Compulsory Third Party Liability (CTPL)](https://help.gcash.com/hc/en-us/articles/10444956195097-FPG-Insurance-Compulsory-Third-Party-Liability-CTPL)\n- [Standard Insurance Car Protect](https://help.gcash.com/hc/en-us/articles/14465379575193-Standard-Insurance-Car-Protect)\n- [Standard Insurance Compulsory Third Party Liability (CTPL)](https://help.gcash.com/hc/en-us/articles/14464629819161-Standard-Insurance-Compulsory-Third-Party-Liability-CTPL)\n\n## Promoted articles\n\n- [What are the steps to get a Fully Verified GCash account?](https://help.gcash.com/hc/en-us/articles/360017722393-What-are-the-steps-to-get-a-Fully-Verified-GCash-account)\n- [Accepted IDs for GCash Verification](https://help.gcash.com/hc/en-us/articles/900000948786-Accepted-IDs-for-GCash-Verification)\n- [How do I send money to another GCash account?](https://help.gcash.com/hc/en-us/articles/360017566614-How-do-I-send-money-to-another-GCash-account)\n\nStandard Insurance Compulsory Third Party Liability or CTPL is an insurance product that covers bodily injury and death caused to a Third Party (person/s) by the Assured and is required by the Land Transportation Office (LTO) upon registration.\n\nJump to:\n\n- [Coverage](https://help.gcash.com/hc/en-us/articles/14464629819161-Standard-Insurance-Compulsory-Third-Party-Liability-CTPL#h_01H2ST5JAKW97AJJVT9Q2FJVNR)\n- [Eligibility](https://help.gcash.com/hc/en-us/articles/14464629819161-Standard-Insurance-Compulsory-Third-Party-Liability-CTPL#h_01H3C4363EHNW62KCYAC8FMRKP)\n- [Purchase Standard Insurance CTPL](https://help.gcash.com/hc/en-us/articles/14464629819161-Standard-Insurance-Compulsory-Third-Party-Liability-CTPL#h_01GPJQB4026SS4JEBKRF7E93YJ)\n- [Claims](https://help.gcash.com/hc/en-us/articles/14464629819161-Standard-Insurance-Compulsory-Third-Party-Liability-CTPL#h_01H3C44RT9VXFD2S354YCY0H1N)\n- [Policy Updates and Cancellations](https://help.gcash.com/hc/en-us/articles/14464629819161-Standard-Insurance-Compulsory-Third-Party-Liability-CTPL#h_01H3C465B2V1FDG164DRJNVGYS)\n- [Contact Standard Insurance](https://help.gcash.com/hc/en-us/articles/14464629819161-Standard-Insurance-Compulsory-Third-Party-Liability-CTPL#h_01H3BWRSNTPY365VNV8MDBT86H)\n\n## Coverage\n\nCTPL is a standalone cover and responds first in the event of a third party’s bodily injury, death, and medical expenses. Standard Insurance will cover a valid claim of up to PHP 100,000, subject to the policy limits.\n\nYour policy can cover you if the insured vehicle gets into an accident while being driven by another person subject to the following conditions:\n\n- You have authorized/permitted them to operate or drive your insured vehicle.\n- The authorized/permitted driver carries a driver’s license.\n- Subject to all other policy terms and conditions.\n\n## Eligibility\n\nYou can avail of this product if you are:\n\n- A [Fully Verified](https://help.gcash.com/hc/en-us/articles/360017722393-How-do-I-get-Fully-Verified-#h_01FPYEDSZ597DXA7JF5NWD6PBC) GCash user\n- The owner of a car that can be insured  - Requirements:    - Private Cars: Sedan, AUV, MPV, Wagon, Van, Pick-up\n    - Age of car up to 15 years old\n    - Usage must be private\n\n**Note:** You can avail as many CTPL policies as you can, depending on the number of cars you own. You may also purchase CTPL by Standard Insurance on behalf of someone else.\n\n## Purchase Standard Insurance CTPL\n\n**Note:** The amount **for the annual premium payment will be automatically deducted from your GCash wallet upon purchase. Please make sure you have enough balance in your GCash wallet to make a successful transaction.**\n\n**![How_to_purchase_CTPL_by_Standard_Insurance.jpg](https://help.gcash.com/hc/article_attachments/14464462680217)**\n\nYour Policy Contract and other Policy Documents will be sent **within an hour** to your registered email address. If you were not able to receive your policy within 24 hours or if you would like to request an original copy of your policy, please [contact Standard Insurance.](https://help.gcash.com/hc/en-us/articles/14464629819161-Standard-Insurance-Compulsory-Third-Party-Liability-CTPL#h_01H3BWRSNTPY365VNV8MDBT86H)\n\nYour CTPL policy will commence based on the last digit of your vehicle’s plate number:\n\n|     |     |\n| --- | --- |\n| **Plate Number** | **Start Date** |\n| Ending in 1 | February 1 |\n| Ending in 2 | March 1 |\n| Ending in 3 | April 1 |\n| Ending in 4 | May 1 |\n| Ending in 5 | June 1 |\n| Ending in 6 | July 1 |\n| Ending in 7 | August 1 |\n| Ending in 8 | September 1 |\n| Ending in 9 | October 1 |\n| Ending in 0 | November 1 |\n\n## Policy Renewal\n\nTo renew your policy, please register your existing policy for online access on the [Standard Insurance website](https://bit.ly/MyStandardOnline).\n\nRegistered policies get a renewal prompt 90 days before policy expiration.  You may renew your policy by [contacting Standard Insurance.](https://help.gcash.com/hc/en-us/articles/14464629819161-Standard-Insurance-Compulsory-Third-Party-Liability-CTPL#h_01H3BWRSNTPY365VNV8MDBT86H)\n\n## Claims\n\n**Note:** Once you have filed a claim and have completed the required documents, reimbursement will be evaluated within 5 days.\n\nYou can file a claim for third-party bodily injury immediately after the occurrence or up to 90 days. To file a claim, please fill out the [Standard Insurance Online Claims Notification form.](https://bit.ly/OnlineClaimNotification)\n\nOnce you have completed the form, attach the necessary requirements:\n\n- Certificate of Registration (CR) and Official Receipt (OR) covering loss date\n- Photocopy of Driver’s license and official receipt\n- Original Police Report\n- Original Medical Certificate\n- Original hospital bills/receipts\n- Birth Certificate (For Minors only)\n\nA representative from Standard Insurance will email you the next steps necessary to process your claim. Claims proceeds may be availed either through check or online transfer. To follow up on your claims, please [contact Standard Insurance.](https://help.gcash.com/hc/en-us/articles/14464629819161-Standard-Insurance-Compulsory-Third-Party-Liability-CTPL#h_01H3BWRSNTPY365VNV8MDBT86H)\n\n## Policy Updates and Cancellations\n\n### Update of CTPL details\n\nIf you have any changes in your policy, please [contact Standard Insurance](https://help.gcash.com/hc/en-us/articles/14464629819161-Standard-Insurance-Compulsory-Third-Party-Liability-CTPL#h_01H3BWRSNTPY365VNV8MDBT86H). Any change or modification in your insured vehicle (i.e. engine no., color, etc.) must be declared in the policy. New details that may be found contrary to the policy that are not properly endorsed may be used as grounds for the denial of the claim.\n\n### Refund and cancellation request\n\nYou may request a refund and cancel your policy within **seven (7) days** of receiving it via email. All premiums shall be returned to your GCash wallet or nominated bank account. provided it is made before 12:00 midnight of the same day of purchase. A representative of Standard Insurance shall process cancellation requests made after the cut-off.\n\nIf the 7-day cancellation period falls on the following month, pro-rata premiums and taxes shall be returned except the documentary stamps.\n\n### Unauthenticated CTPL\n\nYou should be able to receive a notification that your CTPL needs further authentication in your email. A representative from Standard Insurance will contact you to facilitate the authentication. Additional information (i.e., updated plate no., correct motor/serial number) may be required from you to proceed with the authentication.\n\n## Contact Standard Insurance\n\nTo contact Standard Insurance, please check out their available channels below:\n\n- **Email:**  - For Inquiries: [inquiry@standard-insurance.com](mailto:inquiry@standard-insurance.com)\n  - For Claims: [ginsure@standard-insurance.com](mailto:ginsure@standard-insurance.com)\n- **Hotline**  - **Mobile No:** +63917-8283984 (8:00 AM-5:00 PM)\n  - **Landline:** +632-8854-1111 (5:00 PM onwards)\n- **Viber: +63** 998-8451111\n\n[Previous](https://help.gcash.com/hc/en-us/articles/14464629819161-Standard-Insurance-Compulsory-Third-Party-Liability-CTPL#)\n\n[Next](https://help.gcash.com/hc/en-us/articles/14464629819161-Standard-Insurance-Compulsory-Third-Party-Liability-CTPL#)\n\n14464629819161\n\nBack to Top",
  "categories": [
    "BPI MS Compulsory Third Party Liability Insurance",
    "FPG Insurance Compulsory Third Party Liability (CTPL)",
    "Standard Insurance Car Protect",
    "Standard Insurance Compulsory Third Party Liability (CTPL)"
  ],
  "related_articles": [
    {
      "title": "BPI MS Compulsory Third Party Liability Insurance",
      "url": "https://help.gcash.com/hc/en-us/articles/6709500387481-BPI-MS-Compulsory-Third-Party-Liability-Insurance"
    },
    {
      "title": "FPG Insurance Compulsory Third Party Liability (CTPL)",
      "url": "https://help.gcash.com/hc/en-us/articles/10444956195097-FPG-Insurance-Compulsory-Third-Party-Liability-CTPL"
    },
    {
      "title": "Standard Insurance Car Protect",
      "url": "https://help.gcash.com/hc/en-us/articles/14465379575193-Standard-Insurance-Car-Protect"
    },
    {
      "title": "Standard Insurance Compulsory Third Party Liability (CTPL)",
      "url": "https://help.gcash.com/hc/en-us/articles/14464629819161-Standard-Insurance-Compulsory-Third-Party-Liability-CTPL"
    },
    {
      "title": "What are the steps to get a Fully Verified GCash account?",
      "url": "https://help.gcash.com/hc/en-us/articles/360017722393-What-are-the-steps-to-get-a-Fully-Verified-GCash-account"
    },
    {
      "title": "Accepted IDs for GCash Verification",
      "url": "https://help.gcash.com/hc/en-us/articles/900000948786-Accepted-IDs-for-GCash-Verification"
    },
    {
      "title": "How do I send money to another GCash account?",
      "url": "https://help.gcash.com/hc/en-us/articles/360017566614-How-do-I-send-money-to-another-GCash-account"
    },
    {
      "title": "Coverage",
      "url": "https://help.gcash.com/hc/en-us/articles/14464629819161-Standard-Insurance-Compulsory-Third-Party-Liability-CTPL#h_01H2ST5JAKW97AJJVT9Q2FJVNR"
    },
    {
      "title": "Eligibility",
      "url": "https://help.gcash.com/hc/en-us/articles/14464629819161-Standard-Insurance-Compulsory-Third-Party-Liability-CTPL#h_01H3C4363EHNW62KCYAC8FMRKP"
    },
    {
      "title": "Purchase Standard Insurance CTPL",
      "url": "https://help.gcash.com/hc/en-us/articles/14464629819161-Standard-Insurance-Compulsory-Third-Party-Liability-CTPL#h_01GPJQB4026SS4JEBKRF7E93YJ"
    },
    {
      "title": "Claims",
      "url": "https://help.gcash.com/hc/en-us/articles/14464629819161-Standard-Insurance-Compulsory-Third-Party-Liability-CTPL#h_01H3C44RT9VXFD2S354YCY0H1N"
    },
    {
      "title": "Policy Updates and Cancellations",
      "url": "https://help.gcash.com/hc/en-us/articles/14464629819161-Standard-Insurance-Compulsory-Third-Party-Liability-CTPL#h_01H3C465B2V1FDG164DRJNVGYS"
    },
    {
      "title": "Contact Standard Insurance",
      "url": "https://help.gcash.com/hc/en-us/articles/14464629819161-Standard-Insurance-Compulsory-Third-Party-Liability-CTPL#h_01H3BWRSNTPY365VNV8MDBT86H"
    },
    {
      "title": "Fully Verified",
      "url": "https://help.gcash.com/hc/en-us/articles/360017722393-How-do-I-get-Fully-Verified-#h_01FPYEDSZ597DXA7JF5NWD6PBC"
    },
    {
      "title": "contact Standard Insurance.",
      "url": "https://help.gcash.com/hc/en-us/articles/14464629819161-Standard-Insurance-Compulsory-Third-Party-Liability-CTPL#h_01H3BWRSNTPY365VNV8MDBT86H"
    },
    {
      "title": "contacting Standard Insurance.",
      "url": "https://help.gcash.com/hc/en-us/articles/14464629819161-Standard-Insurance-Compulsory-Third-Party-Liability-CTPL#h_01H3BWRSNTPY365VNV8MDBT86H"
    },
    {
      "title": "contact Standard Insurance",
      "url": "https://help.gcash.com/hc/en-us/articles/14464629819161-Standard-Insurance-Compulsory-Third-Party-Liability-CTPL#h_01H3BWRSNTPY365VNV8MDBT86H"
    },
    {
      "title": "Previous",
      "url": "https://help.gcash.com/hc/en-us/articles/14464629819161-Standard-Insurance-Compulsory-Third-Party-Liability-CTPL#"
    },
    {
      "title": "Next",
      "url": "https://help.gcash.com/hc/en-us/articles/14464629819161-Standard-Insurance-Compulsory-Third-Party-Liability-CTPL#"
    }
  ],
  "images": [
    {
      "alt_text": "How_to_purchase_CTPL_by_Standard_Insurance.jpg",
      "url": "https://help.gcash.com/hc/article_attachments/14464462680217"
    }
  ],
  "jump_links": [
    {
      "title": "Coverage",
      "anchor": "https://help.gcash.com/hc/en-us/articles/14464629819161-Standard-Insurance-Compulsory-Third-Party-Liability-CTPL#h_01H2ST5JAKW97AJJVT9Q2FJVNR"
    },
    {
      "title": "Eligibility",
      "anchor": "https://help.gcash.com/hc/en-us/articles/14464629819161-Standard-Insurance-Compulsory-Third-Party-Liability-CTPL#h_01H3C4363EHNW62KCYAC8FMRKP"
    },
    {
      "title": "Purchase Standard Insurance CTPL",
      "anchor": "https://help.gcash.com/hc/en-us/articles/14464629819161-Standard-Insurance-Compulsory-Third-Party-Liability-CTPL#h_01GPJQB4026SS4JEBKRF7E93YJ"
    },
    {
      "title": "Claims",
      "anchor": "https://help.gcash.com/hc/en-us/articles/14464629819161-Standard-Insurance-Compulsory-Third-Party-Liability-CTPL#h_01H3C44RT9VXFD2S354YCY0H1N"
    },
    {
      "title": "Policy Updates and Cancellations",
      "anchor": "https://help.gcash.com/hc/en-us/articles/14464629819161-Standard-Insurance-Compulsory-Third-Party-Liability-CTPL#h_01H3C465B2V1FDG164DRJNVGYS"
    },
    {
      "title": "Contact Standard Insurance",
      "anchor": "https://help.gcash.com/hc/en-us/articles/14464629819161-Standard-Insurance-Compulsory-Third-Party-Liability-CTPL#h_01H3BWRSNTPY365VNV8MDBT86H"
    }
  ],
  "description": "Standard Insurance Compulsory Third Party Liability or CTPL is an insurance product that covers bodily injury and death caused to a Third...",
  "eligibility": "You can avail of this product if you are:\n\n- A [Fully Verified](https://help.gcash.com/hc/en-us/articles/360017722393-How-do-I-get-Fully-Verified-#h_01FPYEDSZ597DXA7JF5NWD6PBC) GCash user\n- The owner of a car that can be insured  - Requirements:    - Private Cars: Sedan, AUV, MPV, Wagon, Van, Pick-up\n    - Age of car up to 15 years old\n    - Usage must be private\n\n**Note:** You can avail as many CTPL policies as you can, depending on the number of cars you own. You may also purchase CTPL by Standard Insurance on behalf of someone else.",
  "coverage": "CTPL is a standalone cover and responds first in the event of a third party’s bodily injury, death, and medical expenses. Standard Insurance will cover a valid claim of up to PHP 100,000, subject to the policy limits.\n\nYour policy can cover you if the insured vehicle gets into an accident while being driven by another person subject to the following conditions:\n\n- You have authorized/permitted them to operate or drive your insured vehicle.\n- The authorized/permitted driver carries a driver’s license.\n- Subject to all other policy terms and conditions."
}